{
  "description": "Seed the Firestore collection 'watchBrands'. Each document id = brand id; fields: name (string), order (number). One flat list, no tiers. Include 'other' as selectable. To seed: use Firebase Console (add each doc) or a one-off script with Admin SDK: for each item in documents, set collection('watchBrands').doc(id).set({ name, order }). App falls back to default list if collection is empty.",
  "collection": "watchBrands",
  "documents": [
    { "id": "rolex", "name": "Rolex", "order": 1 },
    { "id": "patek_philippe", "name": "Patek Philippe", "order": 2 },
    { "id": "audemars_piguet", "name": "Audemars Piguet", "order": 3 },
    { "id": "omega", "name": "Omega", "order": 4 },
    { "id": "cartier", "name": "Cartier", "order": 5 },
    { "id": "tag_heuer", "name": "Tag Heuer", "order": 6 },
    { "id": "breitling", "name": "Breitling", "order": 7 },
    { "id": "iwc", "name": "IWC Schaffhausen", "order": 8 },
    { "id": "panerai", "name": "Panerai", "order": 9 },
    { "id": "jaeger_lecoutre", "name": "Jaeger-LeCoultre", "order": 10 },
    { "id": "vacheron_constantin", "name": "Vacheron Constantin", "order": 11 },
    { "id": "tudor", "name": "Tudor", "order": 12 },
    { "id": "hublot", "name": "Hublot", "order": 13 },
    { "id": "richard_mille", "name": "Richard Mille", "order": 14 },
    { "id": "a_lange_sohne", "name": "A. Lange & Söhne", "order": 15 },
    { "id": "blancpain", "name": "Blancpain", "order": 16 },
    { "id": "breguet", "name": "Breguet", "order": 17 },
    { "id": "chopard", "name": "Chopard", "order": 18 },
    { "id": "girard_perregaux", "name": "Girard-Perregaux", "order": 19 },
    { "id": "piaget", "name": "Piaget", "order": 20 },
    { "id": "zenith", "name": "Zenith", "order": 21 },
    { "id": "bulgari", "name": "Bulgari", "order": 22 },
    { "id": "hermes", "name": "Hermès", "order": 23 },
    { "id": "louis_vuitton", "name": "Louis Vuitton", "order": 24 },
    { "id": "chanel", "name": "Chanel", "order": 25 },
    { "id": "montblanc", "name": "Montblanc", "order": 26 },
    { "id": "grand_seiko", "name": "Grand Seiko", "order": 27 },
    { "id": "seiko", "name": "Seiko", "order": 28 },
    { "id": "citizen", "name": "Citizen", "order": 29 },
    { "id": "casio", "name": "Casio", "order": 30 },
    { "id": "tissot", "name": "Tissot", "order": 31 },
    { "id": "longines", "name": "Longines", "order": 32 },
    { "id": "rado", "name": "Rado", "order": 33 },
    { "id": "mido", "name": "Mido", "order": 34 },
    { "id": "hamilton", "name": "Hamilton", "order": 35 },
    { "id": "oris", "name": "Oris", "order": 36 },
    { "id": "nomos", "name": "Nomos Glashütte", "order": 37 },
    { "id": "glashutte_original", "name": "Glashütte Original", "order": 38 },
    { "id": "baume_mercier", "name": "Baume & Mercier", "order": 39 },
    { "id": "bell_ross", "name": "Bell & Ross", "order": 40 },
    { "id": "bremont", "name": "Bremont", "order": 41 },
    { "id": "maurice_lacroix", "name": "Maurice Lacroix", "order": 42 },
    { "id": "frederique_constant", "name": "Frederique Constant", "order": 43 },
    { "id": "jaquet_droz", "name": "Jaquet Droz", "order": 44 },
    { "id": "ulysse_nardin", "name": "Ulysse Nardin", "order": 45 },
    { "id": "certina", "name": "Certina", "order": 46 },
    { "id": "sinn", "name": "Sinn", "order": 47 },
    { "id": "junghans", "name": "Junghans", "order": 48 },
    { "id": "glycine", "name": "Glycine", "order": 49 },
    { "id": "doxa", "name": "Doxa", "order": 50 },
    { "id": "gucci", "name": "Gucci", "order": 51 },
    { "id": "van_cleef_arpels", "name": "Van Cleef & Arpels", "order": 52 },
    { "id": "ebel", "name": "Ebel", "order": 53 },
    { "id": "corum", "name": "Corum", "order": 54 },
    { "id": "other", "name": "Other", "order": 999 }
  ]
}
